<?xml version='1.0' encoding='ISO-8859-1'?>
<!-- WebCT XML Content generated by WebCT Content Packaging API -->
<manifest identifier='resources' version='1.0'
  xmlns='http://www.imsproject.org/content'
  xmlns:webct='http://www.webct.com/IMS'>
  <metadata>
    <schema>WebCT Content</schema>
    <schemaversion>2.0</schemaversion>
    <lom xmlns='http://www.imsproject.org/metadata'>
      <general>
        <title>
          <langstring xml:lang='en-US'>Programing Eledge-UNAB</langstring>
        </title>
      </general>
      <educational>
        <learningresourcetype>
          <source>
            <langstring xml:lang='x-none'>Eledge</langstring>
          </source>
          <value>
            <langstring xml:lang='x-none'>Content Module</langstring>
          </value>
        </learningresourcetype>
      </educational>
    </lom>
  </metadata>
<organizations>
		<organization identifier='MANIFEST01_ORG1'>
			<webct:properties identifierref='MANIFEST02_ORG1'/>
                    <item identifier='MANIFEST01_ITEM20' identifierref='MANIFEST01_RESOURCE20'>
                        <title>Introducción</title>
                        <item identifier='MANIFEST01_ITEMSUB28' identifierref='MANIFEST01_RESOURCESUB28'>
                                <title>Bienvenidos 1</title>
                        </item>
                        <item identifier='MANIFEST01_ITEMSUB29' identifierref='MANIFEST01_RESOURCESUB29'>
                                <title>Bienvenidos 2</title>
                        </item>
                        <item identifier='MANIFEST01_ITEMSUB52' identifierref='MANIFEST01_RESOURCESUB52'>
                                <title>Error 1200</title>
                        </item>
                        <item identifier='MANIFEST01_ITEMSUB53' identifierref='MANIFEST01_RESOURCESUB53'>
                                <title>trabjaar</title>
                        </item>
                    </item>
                    <item identifier='MANIFEST01_ITEM21' identifierref='MANIFEST01_RESOURCE21'>
                        <title>Como Exportar</title>
                        <item identifier='MANIFEST01_ITEMSUB31' identifierref='MANIFEST01_RESOURCESUB31'>
                                <title>Exportaciòn 1</title>
                        </item>
                        <item identifier='MANIFEST01_ITEMSUB32' identifierref='MANIFEST01_RESOURCESUB32'>
                                <title>Exportaciòn 2</title>
                        </item>
                        <item identifier='MANIFEST01_ITEMSUB33' identifierref='MANIFEST01_RESOURCESUB33'>
                                <title>IMS Exporting</title>
                        </item>
                    </item>
                    <item identifier='MANIFEST01_ITEM23' identifierref='MANIFEST01_RESOURCE23'>
                        <title>Conozcamos UML</title>
                        <item identifier='MANIFEST01_ITEMSUB37' identifierref='MANIFEST01_RESOURCESUB37'>
                                <title>UML</title>
                        </item>
                        <item identifier='MANIFEST01_ITEMSUB38' identifierref='MANIFEST01_RESOURCESUB38'>
                                <title>Casos de Uso</title>
                        </item>
                        <item identifier='MANIFEST01_ITEMSUB39' identifierref='MANIFEST01_RESOURCESUB39'>
                                <title>Casos de Uso Eledge-UNAB</title>
                        </item>
                    </item>
                    <item identifier='MANIFEST01_ITEM31' identifierref='MANIFEST01_RESOURCE31'>
                        <title>Eledge-UNAB</title>
                        <item identifier='MANIFEST01_ITEMSUB50' identifierref='MANIFEST01_RESOURCESUB50'>
                                <title>Clases</title>
                        </item>
                        <item identifier='MANIFEST01_ITEMSUB51' identifierref='MANIFEST01_RESOURCESUB51'>
                                <title>Clases Eledge-UNAB</title>
                        </item>
                    </item>
			</organization>
		</organizations>
			<resources>
					<resource identifier='MANIFEST02_ORG1' type='webctproperties'>
					<file href='resources/data/properties_MANIFEST01_ORG1.xml'/>
				</resource>
					<resource identifier='MANIFEST01_RESOURCE20' type='webcontent' href='resources/20.html'>
					<file href='resources/20.html'/>
					</resource>
					<resource identifier='MANIFEST01_RESOURCESUB28' type='webcontent' href='resources/sub28.html'>
					<file href='resources/sub28.html'/>
					<file href='resources/Eledge/Content/1/tomcat.gif'/>
					</resource>
					<resource identifier='MANIFEST01_RESOURCESUB29' type='webcontent' href='resources/sub29.html'>
					<file href='resources/sub29.html'/>
					</resource>
					<resource identifier='MANIFEST01_RESOURCESUB52' type='webcontent' href='resources/sub52.html'>
					<file href='resources/sub52.html'/>
					</resource>
					<resource identifier='MANIFEST01_RESOURCESUB53' type='webcontent' href='resources/sub53.html'>
					<file href='resources/sub53.html'/>
					</resource>
					<resource identifier='MANIFEST01_RESOURCE21' type='webcontent' href='resources/21.html'>
					<file href='resources/21.html'/>
					</resource>
					<resource identifier='MANIFEST01_RESOURCESUB31' type='webcontent' href='resources/sub31.html'>
					<file href='resources/sub31.html'/>
					<file href='resources/Eledge/Content/1/tomcat.gif'/>
					</resource>
					<resource identifier='MANIFEST01_RESOURCESUB32' type='webcontent' href='resources/sub32.html'>
					<file href='resources/sub32.html'/>
					</resource>
					<resource identifier='MANIFEST01_RESOURCESUB33' type='webcontent' href='resources/sub33.html'>
					<file href='resources/sub33.html'/>
					</resource>
					<resource identifier='MANIFEST01_RESOURCE23' type='webcontent' href='resources/23.html'>
					<file href='resources/23.html'/>
					</resource>
					<resource identifier='MANIFEST01_RESOURCESUB37' type='webcontent' href='resources/sub37.html'>
					<file href='resources/sub37.html'/>
					</resource>
					<resource identifier='MANIFEST01_RESOURCESUB38' type='webcontent' href='resources/sub38.html'>
					<file href='resources/sub38.html'/>
					</resource>
					<resource identifier='MANIFEST01_RESOURCESUB39' type='webcontent' href='resources/sub39.html'>
					<file href='resources/sub39.html'/>
					</resource>
					<resource identifier='MANIFEST01_RESOURCE31' type='webcontent' href='resources/31.html'>
					<file href='resources/31.html'/>
					</resource>
					<resource identifier='MANIFEST01_RESOURCESUB50' type='webcontent' href='resources/sub50.html'>
					<file href='resources/sub50.html'/>
					</resource>
					<resource identifier='MANIFEST01_RESOURCESUB51' type='webcontent' href='resources/sub51.html'>
					<file href='resources/sub51.html'/>
					</resource>
			</resources>
		</manifest>